[null,{"name":"Hoşgeldin","temp":"member","event-type":"6","actions":[{"channel":"4","varName":"","message":"Hoşgeldin ${tempVars(\"member\")}!","storage":"0","varName2":"","name":"Send Message"}]},{"name":"Hoşcakal","temp":"member","event-type":"7","actions":[{"channel":"4","varName":"","message":"${tempVars(\"member\")} Hoşcakal...","storage":"0","varName2":"","name":"Send Message"}]},{"name":"otocevap","temp":"msg","event-type":"2","actions":[{"message":"1","varName":"msg","info":"2","storage":"1","varName2":"text","name":"Store Message Info"},{"storage":"1","varName":"text","comparison":"6","value":"(Selam|sa|merhaba|selam|Sa|Merhaba|SA|MERHABA)","iftrue":"0","iftrueVal":"","iffalse":"1","iffalseVal":"","name":"Check Variable"},{"message":"1","varName":"msg","info":"4","storage":"1","varName2":"channel","name":"Store Message Info"},{"channel":"5","varName":"channel","message":"Merhaba, Hoşgeldin","storage":"0","varName2":"","name":"Send Message"}]},{"name":"otocevap","temp":"msg","event-type":"2","actions":[{"message":"1","varName":"msg","info":"2","storage":"1","varName2":"pepe","name":"Store Message Info"},{"storage":"1","varName":"pepe","comparison":"6","value":"(Akame)","iftrue":"0","iftrueVal":"","iffalse":"1","iffalseVal":"","name":"Check Variable"},{"message":"1","varName":"msg","info":"4","storage":"1","varName2":"channel","name":"Store Message Info"},{"channel":"5","varName":"channel","message":"İyiyim Sen Nasılsın ?","storage":"0","varName2":"","name":"Send Message"}]},{"name":"otocevap","temp":"msg","event-type":"2","actions":[{"message":"1","varName":"msg","info":"2","storage":"1","varName2":"test","name":"Store Message Info"},{"storage":"1","varName":"test","comparison":"6","value":"(Mal)","iftrue":"0","iftrueVal":"","iffalse":"1","iffalseVal":"","name":"Check Variable"},{"message":"1","varName":"msg","info":"2","storage":"1","varName2":"channel","name":"Store Message Info"},{"channel":"5","varName":"channel","message":"Kötü Konuşma","storage":"0","varName2":"","name":"Send Message"}]}]